towel/__init__.py
towel/auth.py
towel/deletion.py
towel/forms.py
towel/managers.py
towel/models.py
towel/modelview.py
towel/paginator.py
towel/queryset_transform.py
towel/quick.py
towel/utils.py
towel/incubator/__init__.py
towel/incubator/frankenresource.py
towel/incubator/modelview.py
towel/locale/de/LC_MESSAGES/django.mo
towel/locale/de/LC_MESSAGES/django.po
towel/mt/__init__.py
towel/mt/api.py
towel/mt/auth.py
towel/mt/forms.py
towel/mt/middleware.py
towel/mt/models.py
towel/mt/modelview.py
towel/resources/__init__.py
towel/resources/base.py
towel/resources/inlines.py
towel/resources/mt.py
towel/resources/urls.py
towel/static/towel/towel.js
towel/static/towel/towel_editlive.js
towel/templates/modelview/object_delete_confirmation.html
towel/templates/modelview/object_detail.html
towel/templates/modelview/object_form.html
towel/templates/modelview/object_list.html
towel/templates/resources/object_delete_confirmation.html
towel/templates/resources/object_detail.html
towel/templates/resources/object_form.html
towel/templates/resources/object_list.html
towel/templates/towel/_form_errors.html
towel/templates/towel/_form_item.html
towel/templates/towel/_form_item_plain.html
towel/templates/towel/_form_warnings.html
towel/templates/towel/_ordering_link.html
towel/templates/towel/_pagination.html
towel/templatetags/__init__.py
towel/templatetags/modelview_detail.py
towel/templatetags/modelview_list.py
towel/templatetags/towel_batch_tags.py
towel/templatetags/towel_form_tags.py
towel/templatetags/towel_region.py
towel/templatetags/towel_resources.py
towel/templatetags/verbose_name_tags.py
towel-0.31.0.dist-info/LICENSE
towel-0.31.0.dist-info/METADATA
towel-0.31.0.dist-info/WHEEL
towel-0.31.0.dist-info/top_level.txt
towel-0.31.0.dist-info/RECORD
