Metadata-Version: 2.1
Name: towel
Version: 0.31.0
Summary: Keeping you DRY since 2010
Home-page: http://github.com/matthiask/towel/
Author: Matthias Kestenholz
Author-email: mk@feinheit.ch
License: BSD License
Platform: OS Independent
Classifier: Development Status :: 5 - Production/Stable
Classifier: Environment :: Web Environment
Classifier: Framework :: Django
Classifier: Intended Audience :: Developers
Classifier: License :: OSI Approved :: BSD License
Classifier: Operating System :: OS Independent
Classifier: Programming Language :: Python
Classifier: Programming Language :: Python :: 3
Classifier: Topic :: Internet :: WWW/HTTP :: Dynamic Content
Classifier: Topic :: Software Development
Classifier: Topic :: Software Development :: Libraries :: Application Frameworks
License-File: LICENSE
Requires-Dist: Django >=3.2
